byted_overpass_iesqa_medialab_evaluate_audio/__init__.py
byted_overpass_iesqa_medialab_evaluate_audio-0.0.1.dist-info/METADATA
byted_overpass_iesqa_medialab_evaluate_audio-0.0.1.dist-info/WHEEL
byted_overpass_iesqa_medialab_evaluate_audio-0.0.1.dist-info/top_level.txt
byted_overpass_iesqa_medialab_evaluate_audio-0.0.1.dist-info/RECORD
